splunk_hec_handler/__init__.py
splunk_hec_handler-1.2.0.dist-info/LICENSE.txt
splunk_hec_handler-1.2.0.dist-info/METADATA
splunk_hec_handler-1.2.0.dist-info/WHEEL
splunk_hec_handler-1.2.0.dist-info/top_level.txt
splunk_hec_handler-1.2.0.dist-info/RECORD
