Metadata-Version: 2.1
Name: splunk-hec-handler
Version: 1.2.0
Summary: A Python logging handler to sends logs to Splunk using HTTP event collector (HEC)
Home-page: https://github.com/vavarachen/splunk_hec_handler
Author: vavarachen
Author-email: vavarachen@gmail.com
License: MIT License
Classifier: Development Status :: 5 - Production/Stable
Classifier: Intended Audience :: Developers
Classifier: License :: OSI Approved :: MIT License
Classifier: Natural Language :: English
Classifier: Operating System :: POSIX :: Linux
Classifier: Operating System :: MacOS :: MacOS X
Classifier: Operating System :: Microsoft :: Windows
Classifier: Programming Language :: Python
Classifier: Programming Language :: Python :: 2.7
Classifier: Programming Language :: Python :: 3.4
Classifier: Programming Language :: Python :: 3.5
Classifier: Programming Language :: Python :: 3.6
Classifier: Programming Language :: Python :: 3.7
Classifier: Programming Language :: Python :: 3.8
Classifier: Topic :: System :: Logging
License-File: LICENSE.txt
Requires-Dist: requests (<3.0.0,>=2.6.0)
Requires-Dist: requests
